xsnumpy/__init__.py
xsnumpy-0.1.dist-info/METADATA
xsnumpy-0.1.dist-info/WHEEL
xsnumpy-0.1.dist-info/top_level.txt
xsnumpy-0.1.dist-info/RECORD
