Metadata-Version: 2.1
Name: xsnumpy
Version: 0.1
Summary: The funniest joke in the world
Home-page: UNKNOWN
Author: Sagar gupta
Author-email: UNKNOWN
License: MIT
Platform: UNKNOWN
